aigc_intent_solt/__init__.py
aigc_intent_solt/app.py
aigc_intent_solt/config/__init__.py
aigc_intent_solt/config/log_config.py
aigc_intent_solt/models/__init__.py
aigc_intent_solt/models/chatbot_model.py
aigc_intent_solt/scene_config/__init__.py
aigc_intent_solt/scene_config/scene_prompts.py
aigc_intent_solt/scene_processor/__init__.py
aigc_intent_solt/scene_processor/scene_processor.py
aigc_intent_solt/scene_processor/impl/__init__.py
aigc_intent_solt/scene_processor/impl/common_processor.py
aigc_intent_solt/utils/__init__.py
aigc_intent_solt/utils/app_init.py
aigc_intent_solt/utils/data_format_utils.py
aigc_intent_solt/utils/date_utils.py
aigc_intent_solt/utils/db_utils.py
aigc_intent_solt/utils/file_utils.py
aigc_intent_solt/utils/helpers.py
aigc_intent_solt/utils/prompt_utils.py
aigc_intent_solt/utils/send_llm.py
aigc_intent_solt-0.1.0.dist-info/METADATA
aigc_intent_solt-0.1.0.dist-info/WHEEL
aigc_intent_solt-0.1.0.dist-info/entry_points.txt
aigc_intent_solt-0.1.0.dist-info/top_level.txt
aigc_intent_solt-0.1.0.dist-info/RECORD
