Metadata-Version: 2.1
Name: aigc-intent-solt
Version: 0.1.0
Summary: AIGC意图解析解决方案
Home-page: http://117.159.24.209:30381/snappy-expand/aigc-intent-solt
Author: Kang Zhao
Author-email: zhaokanga@h3c.com
License: UNKNOWN
Platform: UNKNOWN
Classifier: Programming Language :: Python :: 3
Classifier: License :: OSI Approved :: MIT License
Classifier: Operating System :: OS Independent
Requires-Python: >=3.10
Requires-Dist: flask (>=2.0.3)
Requires-Dist: flask-cors (>=3.0.10)
Requires-Dist: requests (>=2.26.0)
Requires-Dist: python-dotenv (>=0.19.2)
Requires-Dist: sqlalchemy (>=1.4.28)
